scorecard_ai/__init__.py
scorecard_ai/_base_client.py
scorecard_ai/_client.py
scorecard_ai/_compat.py
scorecard_ai/_constants.py
scorecard_ai/_exceptions.py
scorecard_ai/_files.py
scorecard_ai/_models.py
scorecard_ai/_qs.py
scorecard_ai/_resource.py
scorecard_ai/_response.py
scorecard_ai/_streaming.py
scorecard_ai/_types.py
scorecard_ai/_version.py
scorecard_ai/pagination.py
scorecard_ai/py.typed
scorecard_ai/_utils/__init__.py
scorecard_ai/_utils/_compat.py
scorecard_ai/_utils/_datetime_parse.py
scorecard_ai/_utils/_logs.py
scorecard_ai/_utils/_proxy.py
scorecard_ai/_utils/_reflection.py
scorecard_ai/_utils/_resources_proxy.py
scorecard_ai/_utils/_streams.py
scorecard_ai/_utils/_sync.py
scorecard_ai/_utils/_transform.py
scorecard_ai/_utils/_typing.py
scorecard_ai/_utils/_utils.py
scorecard_ai/lib/.keep
scorecard_ai/lib/__init__.py
scorecard_ai/lib/_helpers.py
scorecard_ai/lib/_multi_turn_simulation.py
scorecard_ai/lib/wrap_llms.py
scorecard_ai/resources/__init__.py
scorecard_ai/resources/metrics.py
scorecard_ai/resources/projects.py
scorecard_ai/resources/records.py
scorecard_ai/resources/runs.py
scorecard_ai/resources/scores.py
scorecard_ai/resources/testcases.py
scorecard_ai/resources/testsets.py
scorecard_ai/resources/systems/__init__.py
scorecard_ai/resources/systems/systems.py
scorecard_ai/resources/systems/versions.py
scorecard_ai/types/__init__.py
scorecard_ai/types/metric.py
scorecard_ai/types/metric_create_params.py
scorecard_ai/types/metric_delete_response.py
scorecard_ai/types/metric_list_params.py
scorecard_ai/types/metric_update_params.py
scorecard_ai/types/project.py
scorecard_ai/types/project_create_params.py
scorecard_ai/types/project_list_params.py
scorecard_ai/types/record.py
scorecard_ai/types/record_create_params.py
scorecard_ai/types/record_delete_response.py
scorecard_ai/types/record_list_params.py
scorecard_ai/types/record_list_response.py
scorecard_ai/types/run.py
scorecard_ai/types/run_create_params.py
scorecard_ai/types/run_list_params.py
scorecard_ai-3.6.0.dist-info/METADATA
scorecard_ai-3.6.0.dist-info/WHEEL
scorecard_ai-3.6.0.dist-info/licenses/LICENSE
scorecard_ai-3.6.0.dist-info/RECORD
