Metadata-Version: 2.3
Name: scorecard-ai
Version: 3.6.0
Summary: The official Python library for the Scorecard API
Project-URL: Homepage, https://github.com/scorecard-ai/scorecard-python
Project-URL: Repository, https://github.com/scorecard-ai/scorecard-python
Author-email: Scorecard <team@scorecard.io>
License: Apache-2.0
Classifier: Intended Audience :: Developers
Classifier: License :: OSI Approved :: Apache Software License
Classifier: Operating System :: MacOS
Classifier: Operating System :: Microsoft :: Windows
Classifier: Operating System :: OS Independent
Classifier: Operating System :: POSIX
Classifier: Operating System :: POSIX :: Linux
Classifier: Programming Language :: Python :: 3.9
Classifier: Programming Language :: Python :: 3.10
Classifier: Programming Language :: Python :: 3.11
Classifier: Programming Language :: Python :: 3.12
Classifier: Programming Language :: Python :: 3.13
Classifier: Programming Language :: Python :: 3.14
Classifier: Topic :: Software Development :: Libraries :: Python Modules
Classifier: Typing :: Typed
Requires-Python: >=3.9
Requires-Dist: anyio<5,>=3.5.0
Requires-Dist: distro<2,>=1.7.0
Requires-Dist: httpx<1,>=0.23.0
Requires-Dist: pydantic<3,>=1.9.0
Requires-Dist: sniffio
Requires-Dist: typing-extensions<5,>=4.10
Provides-Extra: aiohttp
Requires-Dist: aiohttp; extra == 'aiohttp'
Requires-Dist: httpx-aiohttp>=0.1.9; extra == 'aiohttp'
Provides-Extra: otel
Requires-Dist: opentelemetry-api>=1.39.1; extra == 'otel'
Requires-Dist: opentelemetry-exporter-otlp-proto-http>=1.39.1; extra == 'otel'
Requires-Dist: opentelemetry-sdk>=1.39.1; extra == 'otel'
